ninja/__init__.py
ninja/py.typed
ninja/ninja_syntax.py
ninja/__main__.py
ninja/_version.py
ninja/data/bin/ninja
mongo_ninja_python_test-1.11.1.0.dist-info/entry_points.txt
mongo_ninja_python_test-1.11.1.0.dist-info/METADATA
mongo_ninja_python_test-1.11.1.0.dist-info/RECORD
mongo_ninja_python_test-1.11.1.0.dist-info/top_level.txt
mongo_ninja_python_test-1.11.1.0.dist-info/LICENSE_Apache_20
mongo_ninja_python_test-1.11.1.0.dist-info/WHEEL
mongo_ninja_python_test-1.11.1.0.dist-info/AUTHORS.rst
